fast_jl_binary.cpython-310-x86_64-linux-gnu.so
fast_jl_binary-0.1.3.3.dist-info/METADATA
fast_jl_binary-0.1.3.3.dist-info/WHEEL
fast_jl_binary-0.1.3.3.dist-info/top_level.txt
fast_jl_binary-0.1.3.3.dist-info/RECORD
