Metadata-Version: 2.4
Name: fast_jl_binary
Version: 0.1.3.3
Summary: Fast JL: Compute JL projection fast on a GPU (Binary Distribution)
Author: Dariush Wahdany
Author-email: dariushwahdany@gmail.com
Requires-Dist: torch>=2.0.0
Dynamic: author
Dynamic: author-email
Dynamic: description
Dynamic: requires-dist
Dynamic: summary
